richpyls/__init__.py
richpyls/__main__.py
richpyls-0.1.3.dist-info/METADATA
richpyls-0.1.3.dist-info/WHEEL
richpyls-0.1.3.dist-info/entry_points.txt
richpyls-0.1.3.dist-info/licenses/LICENSE
richpyls-0.1.3.dist-info/RECORD
