Metadata-Version: 2.4
Name: richpyls
Version: 0.1.3
Summary: A modern, type-annotated Python implementation of the Unix ls command with beautiful Rich formatting and color-coded file types
Project-URL: Homepage, https://github.com/lpozo/richpyls
Project-URL: Bug Reports, https://github.com/lpozo/richpyls/issues
Project-URL: Source, https://github.com/lpozo/richpyls
Project-URL: Documentation, https://github.com/lpozo/richpyls#readme
Author-email: Leodanis Pozo Ramos <lpozor78@gmail.com>
Maintainer-email: Leodanis Pozo Ramos <lpozor78@gmail.com>
License-Expression: MIT
License-File: LICENSE
Keywords: cli,command-line,directory,file-listing,ls,tree,tree-view,unix
Classifier: Development Status :: 4 - Beta
Classifier: Environment :: Console
Classifier: Intended Audience :: Developers
Classifier: Intended Audience :: System Administrators
Classifier: License :: OSI Approved :: MIT License
Classifier: Operating System :: OS Independent
Classifier: Programming Language :: Python :: 3
Classifier: Programming Language :: Python :: 3 :: Only
Classifier: Programming Language :: Python :: 3.13
Classifier: Topic :: System :: Filesystems
Classifier: Topic :: Utilities
Classifier: Typing :: Typed
Requires-Python: >=3.13
Requires-Dist: click>=8.2.1
Requires-Dist: rich>=14.0.0
